Metadata-Version: 1.1
Name: ssdb
Version: 0.0.2
Summary: Python client for SSDB
Home-page: https://github.com/wrongwaycn/ssdb-py
Author: wrongwaycn
Author-email: wrongwaycn@gmail.com
License: BSD-2
Keywords: SSDB
Platform: UNKNOWN
Classifier: Development Status :: 5 - Production/Stable
Classifier: Environment :: Console
Classifier: Intended Audience :: Developers
Classifier: License :: OSI Approved :: BSD License
Classifier: Operating System :: OS Independent
Classifier: Programming Language :: Python
Classifier: Programming Language :: Python :: 2.5
Classifier: Programming Language :: Python :: 2.6
Classifier: Programming Language :: Python :: 2.7
Classifier: Programming Language :: Python :: 3
Classifier: Programming Language :: Python :: 3.2
Classifier: Programming Language :: Python :: 3.3
